tokenizer/__init__.py
tokenizer/__version__.py
tokenizer/benchmark_scenarios.py
tokenizer/cli.py
tokenizer/evaluation.py
tokenizer/memory_profiler.py
tokenizer/memory_utils.py
tokenizer/post_processor.py
tokenizer/pre_tokenizer.py
tokenizer/py.typed
tokenizer/tokenizer.py
tokenizer/trainer.py
tokenizer/vocab.py
ultra_tokenizer-0.1.3.dist-info/licenses/LICENSE
ultra_tokenizer-0.1.3.dist-info/METADATA
ultra_tokenizer-0.1.3.dist-info/WHEEL
ultra_tokenizer-0.1.3.dist-info/entry_points.txt
ultra_tokenizer-0.1.3.dist-info/top_level.txt
ultra_tokenizer-0.1.3.dist-info/RECORD
