Metadata-Version: 2.4
Name: ultra-tokenizer
Version: 0.1.3
Summary: Advanced tokenizer with support for BPE, WordPiece, and Unigram algorithms
Home-page: https://github.com/pranav271103/Ultra-Tokenizer.git
Author: Pranav Singh
Author-email: Pranav Singh <pranav.singh01010101@gmail.com>
License: Apache-2.0
Project-URL: Homepage, https://github.com/pranav271103/Ultra-Tokenizer.git
Project-URL: Documentation, https://github.com/pranav271103/Ultra-Tokenizer.git#readme
Project-URL: Bug Tracker, https://github.com/pranav271103/Ultra-Tokenizer/issues
Project-URL: Source Code, https://github.com/pranav271103/Ultra-Tokenizer.git
Keywords: tokenizer,nlp,bpe,wordpiece,unigram
Classifier: Development Status :: 4 - Beta
Classifier: Intended Audience :: Science/Research
Classifier: Intended Audience :: Developers
Classifier: License :: OSI Approved :: Apache Software License
Classifier: Programming Language :: Python :: 3
Classifier: Programming Language :: Python :: 3.8
Classifier: Programming Language :: Python :: 3.9
Classifier: Programming Language :: Python :: 3.10
Classifier: Programming Language :: Python :: 3.11
Classifier: Programming Language :: Python :: 3.12
Classifier: Topic :: Scientific/Engineering
Classifier: Topic :: Software Development
Classifier: Topic :: Text Processing
Classifier: Typing :: Typed
Requires-Python: >=3.8
License-File: LICENSE
Requires-Dist: regex>=2023.6.3
Requires-Dist: tqdm>=4.65.0
Requires-Dist: numpy>=1.21.0
Provides-Extra: dev
Requires-Dist: pytest>=7.0.0; extra == "dev"
Requires-Dist: pytest-cov>=4.0.0; extra == "dev"
Requires-Dist: black>=23.0.0; extra == "dev"
Requires-Dist: isort>=5.12.0; extra == "dev"
Requires-Dist: mypy>=1.0.0; extra == "dev"
Requires-Dist: pylint>=2.15.0; extra == "dev"
Dynamic: author
Dynamic: home-page
Dynamic: license-file
Dynamic: requires-python
